{
  "modules": [
    {
      "id": "newsmobile",
      "files": [
        "NewsMobile/ContentView.swift",
        "NewsMobile/NewsMobileApp.swift",
        "NewsMobile/NovaAPIServer.swift"
      ],
      "imports": [
        "BackgroundTasks",
        "Foundation",
        "Network",
        "SwiftUI"
      ],
      "types": [
        {
          "kind": "struct",
          "name": "ContentView"
        },
        {
          "kind": "enum",
          "name": "SnapshotScreen"
        },
        {
          "kind": "struct",
          "name": "SnapshotSupport"
        },
        {
          "kind": "struct",
          "name": "SnapshotRootView"
        },
        {
          "kind": "struct",
          "name": "NewsMobileApp"
        },
        {
          "kind": "class",
          "name": "NovaAPIServer"
        },
        {
          "kind": "struct",
          "name": "NovaRequest"
        }
      ],
      "views": [
        "ContentView",
        "SnapshotRootView"
      ],
      "function_count": 11,
      "capability_hints": []
    },
    {
      "id": "newsmobile.ml",
      "files": [
        "NewsMobile/ML/EntityExtractor.swift",
        "NewsMobile/ML/SentimentAnalyzer.swift"
      ],
      "imports": [
        "Foundation",
        "NaturalLanguage"
      ],
      "types": [
        {
          "kind": "class",
          "name": "EntityExtractor"
        },
        {
          "kind": "class",
          "name": "SentimentAnalyzer"
        }
      ],
      "views": [],
      "function_count": 2,
      "capability_hints": []
    },
    {
      "id": "newsmobile.models",
      "files": [
        "NewsMobile/Models/AIBackendManager+Enhanced.swift",
        "NewsMobile/Models/AIBackendManager+Generation.swift",
        "NewsMobile/Models/AIBackendManager.swift",
        "NewsMobile/Models/AIBackendStatusMenu.swift",
        "NewsMobile/Models/NewsModels.swift"
      ],
      "imports": [
        "AppKit",
        "Combine",
        "Foundation",
        "SwiftUI"
      ],
      "types": [
        {
          "kind": "struct",
          "name": "ConnectionTestResult"
        },
        {
          "kind": "struct",
          "name": "UsageStats"
        },
        {
          "kind": "struct",
          "name": "PerformanceMetrics"
        },
        {
          "kind": "struct",
          "name": "OllamaResponse"
        },
        {
          "kind": "struct",
          "name": "OpenAIResponse"
        },
        {
          "kind": "struct",
          "name": "Choice"
        },
        {
          "kind": "struct",
          "name": "Message"
        },
        {
          "kind": "enum",
          "name": "AIError"
        },
        {
          "kind": "class",
          "name": "AIBackendManager"
        },
        {
          "kind": "enum",
          "name": "AIBackend"
        },
        {
          "kind": "struct",
          "name": "OllamaResponse"
        },
        {
          "kind": "struct",
          "name": "Model"
        },
        {
          "kind": "struct",
          "name": "AIBackendSelectionView"
        },
        {
          "kind": "struct",
          "name": "BackendStatusRow"
        },
        {
          "kind": "struct",
          "name": "AIBackendStatusMenu"
        },
        {
          "kind": "struct",
          "name": "AIBackendStatusMenuCompact"
        },
        {
          "kind": "struct",
          "name": "AIBackendStatusMenu_Previews"
        },
        {
          "kind": "enum",
          "name": "NewsCategory"
        },
        {
          "kind": "enum",
          "name": "SourceBias"
        },
        {
          "kind": "struct",
          "name": "NewsSource"
        },
        {
          "kind": "struct",
          "name": "NewsArticle"
        },
        {
          "kind": "struct",
          "name": "SentimentResult"
        },
        {
          "kind": "enum",
          "name": "SentimentLabel"
        },
        {
          "kind": "struct",
          "name": "ExtractedEntity"
        },
        {
          "kind": "enum",
          "name": "EntityType"
        },
        {
          "kind": "struct",
          "name": "StoryCluster"
        },
        {
          "kind": "struct",
          "name": "PerspectiveBreakdown"
        },
        {
          "kind": "struct",
          "name": "WatchLaterItem"
        },
        {
          "kind": "struct",
          "name": "KeywordAlert"
        },
        {
          "kind": "struct",
          "name": "CustomRSSFeed"
        },
        {
          "kind": "struct",
          "name": "TrendingTopic"
        },
        {
          "kind": "struct",
          "name": "WeatherData"
        },
        {
          "kind": "struct",
          "name": "NewsMobileSettings"
        },
        {
          "kind": "enum",
          "name": "SpeechRate"
        },
        {
          "kind": "enum",
          "name": "FontSize"
        },
        {
          "kind": "struct",
          "name": "UserPreferenceProfile"
        }
      ],
      "views": [
        "AIBackendSelectionView",
        "AIBackendStatusMenu",
        "AIBackendStatusMenuCompact",
        "BackendStatusRow"
      ],
      "function_count": 41,
      "capability_hints": []
    },
    {
      "id": "newsmobile.services",
      "files": [
        "NewsMobile/Services/BackgroundRefreshManager.swift",
        "NewsMobile/Services/CloudSyncManager.swift",
        "NewsMobile/Services/ContentFilter.swift",
        "NewsMobile/Services/CustomFeedManager.swift",
        "NewsMobile/Services/KeywordAlertManager.swift",
        "NewsMobile/Services/LocalNewsService.swift",
        "NewsMobile/Services/NewsAggregator.swift",
        "NewsMobile/Services/NotificationManager.swift",
        "NewsMobile/Services/PersonalizationEngine.swift",
        "NewsMobile/Services/RSSParser.swift",
        "NewsMobile/Services/SettingsManager.swift",
        "NewsMobile/Services/StoryClusterEngine.swift",
        "NewsMobile/Services/TTSManager.swift",
        "NewsMobile/Services/TrendingTopicsEngine.swift",
        "NewsMobile/Services/WatchLaterManager.swift",
        "NewsMobile/Services/WeatherService.swift",
        "NewsMobile/Services/WidgetDataManager.swift"
      ],
      "imports": [
        "AVFoundation",
        "BackgroundTasks",
        "CoreLocation",
        "Foundation",
        "NaturalLanguage",
        "SwiftUI",
        "UserNotifications",
        "WidgetKit"
      ],
      "types": [
        {
          "kind": "class",
          "name": "BackgroundRefreshManager"
        },
        {
          "kind": "class",
          "name": "CloudSyncManager"
        },
        {
          "kind": "class",
          "name": "ContentFilter"
        },
        {
          "kind": "class",
          "name": "CustomFeedManager"
        },
        {
          "kind": "class",
          "name": "KeywordAlertManager"
        },
        {
          "kind": "class",
          "name": "LocalNewsService"
        },
        {
          "kind": "class",
          "name": "NewsAggregator"
        },
        {
          "kind": "class",
          "name": "NotificationManager"
        },
        {
          "kind": "class",
          "name": "PersonalizationEngine"
        },
        {
          "kind": "class",
          "name": "XMLParserBuffer"
        },
        {
          "kind": "struct",
          "name": "RawItem"
        },
        {
          "kind": "actor",
          "name": "RSSParser"
        },
        {
          "kind": "actor",
          "name": "hops"
        },
        {
          "kind": "class",
          "name": "SettingsManager"
        },
        {
          "kind": "class",
          "name": "StoryClusterEngine"
        },
        {
          "kind": "class",
          "name": "TTSManager"
        },
        {
          "kind": "class",
          "name": "TrendingTopicsEngine"
        },
        {
          "kind": "class",
          "name": "WatchLaterManager"
        },
        {
          "kind": "class",
          "name": "WeatherService"
        },
        {
          "kind": "class",
          "name": "WidgetDataManager"
        },
        {
          "kind": "enum",
          "name": "Keys"
        },
        {
          "kind": "struct",
          "name": "NewsArticle"
        },
        {
          "kind": "enum",
          "name": "NewsCategory"
        },
        {
          "kind": "enum",
          "name": "Sentiment"
        }
      ],
      "views": [],
      "function_count": 88,
      "capability_hints": [
        "location.corelocation",
        "media.avfoundation",
        "notification.usernotifications",
        "widget.widgetkit"
      ]
    },
    {
      "id": "newsmobile.views",
      "files": [
        "NewsMobile/Views/ArticleDetailView.swift",
        "NewsMobile/Views/ArticleWebView.swift",
        "NewsMobile/Views/AudioBriefingView.swift",
        "NewsMobile/Views/CategoryView.swift",
        "NewsMobile/Views/CustomFeedsView.swift",
        "NewsMobile/Views/ForYouView.swift",
        "NewsMobile/Views/HomeView.swift",
        "NewsMobile/Views/KeywordAlertsView.swift",
        "NewsMobile/Views/LocalNewsView.swift",
        "NewsMobile/Views/SearchView.swift",
        "NewsMobile/Views/SettingsView.swift",
        "NewsMobile/Views/StoryClusterView.swift",
        "NewsMobile/Views/WatchLaterView.swift"
      ],
      "imports": [
        "SwiftUI",
        "WebKit"
      ],
      "types": [
        {
          "kind": "struct",
          "name": "ArticleDetailView"
        },
        {
          "kind": "struct",
          "name": "SentimentBadge"
        },
        {
          "kind": "struct",
          "name": "BiasIndicatorBadge"
        },
        {
          "kind": "struct",
          "name": "EntityBadge"
        },
        {
          "kind": "struct",
          "name": "FlowLayout"
        },
        {
          "kind": "struct",
          "name": "ArticleWebView"
        },
        {
          "kind": "struct",
          "name": "WebView"
        },
        {
          "kind": "class",
          "name": "Coordinator"
        },
        {
          "kind": "struct",
          "name": "AudioBriefingView"
        },
        {
          "kind": "struct",
          "name": "CategoryView"
        },
        {
          "kind": "struct",
          "name": "CustomFeedsView"
        },
        {
          "kind": "struct",
          "name": "CustomFeedRow"
        },
        {
          "kind": "struct",
          "name": "AddFeedView"
        },
        {
          "kind": "struct",
          "name": "ForYouView"
        },
        {
          "kind": "struct",
          "name": "HomeView"
        },
        {
          "kind": "struct",
          "name": "CategoryButton"
        },
        {
          "kind": "struct",
          "name": "KeywordAlertsView"
        },
        {
          "kind": "struct",
          "name": "KeywordRow"
        },
        {
          "kind": "struct",
          "name": "KeywordMatchesView"
        },
        {
          "kind": "struct",
          "name": "ArticleRow"
        },
        {
          "kind": "struct",
          "name": "LocalNewsView"
        },
        {
          "kind": "struct",
          "name": "LocationPickerView"
        },
        {
          "kind": "struct",
          "name": "SearchView"
        },
        {
          "kind": "struct",
          "name": "SearchResultRow"
        },
        {
          "kind": "struct",
          "name": "SettingsView"
        },
        {
          "kind": "struct",
          "name": "StoryClusterView"
        },
        {
          "kind": "struct",
          "name": "SourceChip"
        },
        {
          "kind": "struct",
          "name": "PerspectiveSection"
        },
        {
          "kind": "struct",
          "name": "PerspectiveCard"
        },
        {
          "kind": "struct",
          "name": "WatchLaterView"
        },
        {
          "kind": "struct",
          "name": "WatchLaterRow"
        }
      ],
      "views": [
        "AddFeedView",
        "ArticleDetailView",
        "ArticleRow",
        "ArticleWebView",
        "AudioBriefingView",
        "BiasIndicatorBadge",
        "CategoryButton",
        "CategoryView",
        "CustomFeedRow",
        "CustomFeedsView",
        "EntityBadge",
        "ForYouView",
        "HomeView",
        "KeywordAlertsView",
        "KeywordMatchesView",
        "KeywordRow",
        "LocalNewsView",
        "LocationPickerView",
        "PerspectiveCard",
        "PerspectiveSection",
        "SearchResultRow",
        "SearchView",
        "SentimentBadge",
        "SettingsView",
        "SourceChip",
        "StoryClusterView",
        "WatchLaterRow",
        "WatchLaterView"
      ],
      "function_count": 10,
      "capability_hints": [
        "webview.webkit"
      ]
    },
    {
      "id": "newsmobiletests",
      "files": [
        "NewsMobileTests/NewsMobileTests.swift"
      ],
      "imports": [
        "SwiftUI",
        "XCTest"
      ],
      "types": [
        {
          "kind": "enum",
          "name": "TestData"
        },
        {
          "kind": "class",
          "name": "NewsArticleModelTests"
        },
        {
          "kind": "class",
          "name": "NewsCategoryModelTests"
        },
        {
          "kind": "class",
          "name": "SourceBiasTests"
        },
        {
          "kind": "class",
          "name": "NewsSourceModelTests"
        },
        {
          "kind": "class",
          "name": "SentimentResultTests"
        },
        {
          "kind": "class",
          "name": "ExtractedEntityTests"
        },
        {
          "kind": "class",
          "name": "StoryClusterTests"
        },
        {
          "kind": "class",
          "name": "WatchLaterItemTests"
        },
        {
          "kind": "class",
          "name": "KeywordAlertTests"
        },
        {
          "kind": "class",
          "name": "CustomRSSFeedTests"
        },
        {
          "kind": "class",
          "name": "SettingsTests"
        },
        {
          "kind": "class",
          "name": "UserPreferenceProfileTests"
        },
        {
          "kind": "class",
          "name": "ColorExtensionTests"
        },
        {
          "kind": "class",
          "name": "SecurityTests"
        },
        {
          "kind": "class",
          "name": "TrendingTopicTests"
        },
        {
          "kind": "class",
          "name": "PerspectiveBreakdownTests"
        },
        {
          "kind": "class",
          "name": "FrameTests"
        }
      ],
      "views": [],
      "function_count": 87,
      "capability_hints": []
    },
    {
      "id": "newsmobilewidget",
      "files": [
        "NewsMobileWidget/NewsMobileWidget.swift"
      ],
      "imports": [
        "SwiftUI",
        "WidgetKit"
      ],
      "types": [
        {
          "kind": "struct",
          "name": "NewsEntry"
        },
        {
          "kind": "struct",
          "name": "HeadlineItem"
        },
        {
          "kind": "struct",
          "name": "WeatherData"
        },
        {
          "kind": "struct",
          "name": "NewsProvider"
        },
        {
          "kind": "struct",
          "name": "NewsWidgetEntryView"
        },
        {
          "kind": "struct",
          "name": "SmallNewsWidget"
        },
        {
          "kind": "struct",
          "name": "MediumNewsWidget"
        },
        {
          "kind": "struct",
          "name": "LargeNewsWidget"
        },
        {
          "kind": "struct",
          "name": "NewsHeadlineRow"
        },
        {
          "kind": "struct",
          "name": "NewsMobileWidget"
        }
      ],
      "views": [
        "LargeNewsWidget",
        "MediumNewsWidget",
        "NewsHeadlineRow",
        "NewsWidgetEntryView",
        "SmallNewsWidget"
      ],
      "function_count": 10,
      "capability_hints": [
        "widget.widgetkit"
      ]
    },
    {
      "id": "views.components",
      "files": [
        "NewsMobile/Views/Components/ArticleCard.swift",
        "NewsMobile/Views/Components/BreakingNewsBanner.swift",
        "NewsMobile/Views/Components/TrendingBar.swift",
        "NewsMobile/Views/Components/WeatherWidget.swift"
      ],
      "imports": [
        "SwiftUI"
      ],
      "types": [
        {
          "kind": "struct",
          "name": "ArticleCard"
        },
        {
          "kind": "struct",
          "name": "BreakingNewsBanner"
        },
        {
          "kind": "struct",
          "name": "TrendingBar"
        },
        {
          "kind": "struct",
          "name": "TrendingChip"
        },
        {
          "kind": "struct",
          "name": "WeatherWidget"
        }
      ],
      "views": [
        "ArticleCard",
        "BreakingNewsBanner",
        "TrendingBar",
        "TrendingChip",
        "WeatherWidget"
      ],
      "function_count": 0,
      "capability_hints": []
    }
  ]
}